<?xml version="1.0" encoding="UTF-8"?>
<contents className="m10c01s12">
	<transcript>
		<text path="" id="0"><![CDATA[]]></text>
	</transcript>
	 <contentBackground>		
		<img path="content/images/ltr/module10/m10c01/m10c01s12/contentBackground.jpg" minwidth="769"><![CDATA[봉투에 들어 있는 돈 ]]></img>
	</contentBackground>
	 <contentBg style=""></contentBg>
    <panelText>
		<text width="500px" height="auto" top="0px" position="relative" left="0px" padding="" cName=""><![CDATA[급행료는 뇌물 수수의 한 형태입니다. 뇌물 수수는 다른 사람의 업무와 관련하여 그 사람에게 영향을 미칠 목적으로 가치 있는 것을 제안, 제공, 수령 또는 요청하는 것을 말합니다.]]></text>
		<text width="500px" height="auto" top="10px" position="relative" left="0px" padding="" cName=""><![CDATA[부패방지법에 따라 뇌물을 제공하는 것은 불법이며, 특히 영국 뇌물 수수법에 의하면 뇌물을 주는 것뿐만 아니라 받는 것도 불법입니다. Johnson Controls가 사실관계를 몰랐다 하더라도 회사를 대신하는 사람이 준 뇌물에 대해 책임을 지게 될 수 있습니다.]]></text>
		<text width="500px" height="auto" top="20px" position="relative" left="0px" padding="" cName=""><![CDATA[Johnson Controls 같은 다국적 기업의 경우, 어느 지역에서든 부정행위가 발생하면 회사, 직원 및 비즈니스 파트너가 거의 모든 해당 지역에서 법 집행을 받게 되어 있습니다.]]></text>
		<text width="500px" height="auto" top="30px" position="relative" left="0px" padding="0 0 30px 0" cName=""><![CDATA[뇌물로 해석될 수 있는 것을 요청받거나 제안받는 경우, 즉시 해당 대화를 종료하고 법무 또는 규정 준수팀에 보고해야 합니다.]]></text>
	</panelText>	
	<pageTitle style="width: 500px;"></pageTitle>
	<instructionText style="width: 500px;">
		<text><![CDATA[계속하려면 '다음'을 클릭하십시오.]]></text>
	</instructionText>
</contents>