<?xml version="1.0" encoding="UTF-8"?>
<contents className="m10c02s10">
	<transcript>
		<text path="" id="0"><![CDATA[]]></text>
	</transcript>
	<contentBg style="" wtbgStyle=""></contentBg>
	<pageTitle style=""></pageTitle>
	 <contentBackground>		
		<img path="content/images/ltr/module10/m10c02/m10c02s10/contentBackground.jpg" minwidth="769"><![CDATA[]]></img>
	</contentBackground>
	<contentText>
		<text position="relative" width="900px" height="auto" left="0" top="0px"><![CDATA[艾玛的同事珊迪正要去往艾玛的一个房源，路上发生了车祸。 艾玛去医院探望她。]]></text>
	</contentText>
	<instructionText>
		<text><![CDATA[单击故事的各个阶段。]]></text>
		<text><![CDATA[单击“下一步”继续。]]></text>
	</instructionText>
	<comicStrip imgWidth="126">
		<strip id="1">
			<stripThumImg numberText="1">	
				<img path="content/images/ltr/module10/m10c02/m10c02s10/Page_10_Tumb_01.png" minwidth="700" minheight="550" />
				<title><![CDATA[]]></title>
			</stripThumImg>	
			<stripBackground>			
				<img path="content/images/ltr/module10/m10c02/m10c02s10/Page_10_Strip_01.png" minwidth="700" minheight="550"><![CDATA[]]></img>			
			</stripBackground>
			<stripCallOut align="" isThoughtbubble="" stripNonBg="true" showArrow="false" bColor="#0158A6" color="#FFFFFF" textAlign="center">
				<callOut minwidth="700" minheight="550" x="14" y="245" width="338" />
				<text><![CDATA[<span style="font-weight: bold;">艾玛</span>是 Johnson Controls 的客户服务代表]]></text>
			</stripCallOut>
			<stripCallOut align="" isThoughtbubble="" stripNonBg="true" showArrow="false" bColor="#0158A6" color="#FFFFFF" textAlign="center">
				<callOut minwidth="700" minheight="550" x="604" y="245" width="200" />
				<text><![CDATA[<span style="font-weight: bold;">珊迪</span>是一名会计助理]]></text>			
			</stripCallOut>
		</strip>
		
		<strip id="2">
			<stripThumImg numberText="2">
				<img path="content/images/ltr/module10/m10c02/m10c02s10/Page_10_Tumb_02.png" minwidth="700" minheight="550" />
				<title><![CDATA[]]></title>
			</stripThumImg>
			<stripBackground>				
				<img path="content/images/ltr/module10/m10c02/m10c02s10/Page_10_Strip_02.png" minwidth="700" minheight="550"><![CDATA[]]></img>	
			</stripBackground>
			<stripCallOut align="right" isThoughtbubble="false">
				<callOut minwidth="700" minheight="550" x="95" y="42" width="170" />
				<text><![CDATA[珊迪，你感觉怎么样了？]]></text>
			</stripCallOut>
			<stripCallOut align="left" isThoughtbubble="false">
				<callOut minwidth="700" minheight="550" x="578" y="100" width="170" arrowStyle="top:70px;" />
				<text><![CDATA[额，不太好。 我脑海中不断回放着那场车祸，好像是凭空而来的一样。  那个家伙闯了红灯，警察告诉我他开车的时候在发短信。]]></text>
			</stripCallOut>
		</strip>
		
		<strip id="3">
			<stripThumImg numberText="3">	
				<img path="content/images/ltr/module10/m10c02/m10c02s10/Page_10_Tumb_03.png" minwidth="700" minheight="550" />
				<title><![CDATA[]]></title>
			</stripThumImg>
			<stripBackground>				
				<img path="content/images/ltr/module10/m10c02/m10c02s10/Page_10_Strip_03.png" minwidth="700" minheight="550"><![CDATA[]]></img>		
			</stripBackground>
			<stripCallOut align="right" isThoughtbubble="false">
				<callOut minwidth="700" minheight="550" x="95" y="42" width="170" />
				<text><![CDATA[发生这种事我感到很难过。 你妈妈和我说，你的腿可能还要再做几次手术。]]></text>
			</stripCallOut>
			<stripCallOut align="left" isThoughtbubble="false">
				<callOut minwidth="700" minheight="550" x="578" y="50" width="170" arrowStyle="top:121px;" />
				<text><![CDATA[是的，而且还要做很多理疗。 但这还不是最糟的。 医生认为我的脑部可能也受到损伤。 我的头一直很疼，而且我的平衡感和协调能力都很糟糕。 我想我可能有一阵子不能工作了。]]></text>			
			</stripCallOut>
		</strip>
		
		<strip id="4">
			<stripThumImg numberText="4">	
				<img path="content/images/ltr/module10/m10c02/m10c02s10/Page_10_Tumb_04.png" minwidth="700" minheight="550" />
				<title><![CDATA[]]></title>
			</stripThumImg>
			<stripBackground>				
				<img path="content/images/ltr/module10/m10c02/m10c02s10/Page_10_Strip_04.png" minwidth="700" minheight="550"><![CDATA[]]></img>		
			</stripBackground>
			<stripCallOut align="right" isThoughtbubble="false">
				<callOut minwidth="700" minheight="550" x="129" y="57" width="140" arrowStyle="top:10px;" />
				<text><![CDATA[哦，真是太糟了，珊迪。]]></text>
			</stripCallOut>
		<stripCallOut align="bottomleft" isThoughtbubble="false">
				<callOut minwidth="700" minheight="550" x="398" y="10" width="360" arrowStyle="left: 85px;" />
				<text><![CDATA[即使我有医保，医疗费用还是非常昂贵。 而且我也不知道自己要失业多久。 我不知道怎样才能付得起所有这些费用。]]></text>			
				<text><![CDATA[我的家人帮我募集善款承担费用，我想他们甚至建立了 Facebook 专页，但是我讨厌向他人求助，我希望个人私事不要外扬。]]></text>			
			</stripCallOut>
		</strip>

	</comicStrip>
</contents>