<?xml version="1.0" encoding="UTF-8"?>
<contents className="m08s08">
	<transcript>
		<text path="" id="0"><![CDATA[]]></text>
	</transcript>
	<contentText>
		<text position="" top="" fontSize=""><![CDATA[]]></text>
	</contentText>
	<contentBackground>
		<img path="content/images/ltr/module8/m08s08/contentBackground.jpg" minwidth="769"><![CDATA[]]></img>
	</contentBackground>
	<pageTitle style="width: 648px;margin-bottom: 5px;"></pageTitle>
	<instructionText style="width: 648px;">
		<text><![CDATA[Kliknite na položku Prehrať.]]></text>
		<text><![CDATA[Ak sa chcete dozvedieť viac, kliknite na šípku.]]></text>
		<text><![CDATA[Pokračujte kliknutím na tlačidlo Ďalej.]]></text>
	</instructionText>
	
	<stripContent imgWidth="18">
		<strip id="1">
			<stripBackground>			
				<img path="content/images/ltr/module8/m08s08/slk/Strip_01.png" minwidth="700" minheight="550"><![CDATA[]]></img>	
			</stripBackground>
		</strip>
		<strip id="2">
			<stripBackground>			
				<img path="content/images/ltr/module8/m08s08/slk/Strip_02.png" minwidth="700" minheight="550"><![CDATA[]]></img>	
			</stripBackground>
		</strip>
		<strip id="3">
			<stripBackground>			
				<img path="content/images/ltr/module8/m08s08/slk/Strip_03.png" minwidth="700" minheight="550"><![CDATA[]]></img>	
			</stripBackground>
		</strip>
		<strip id="4">
			<stripBackground>			
				<img path="content/images/ltr/module8/m08s08/slk/Strip_04.png" minwidth="700" minheight="550"><![CDATA[]]></img>	
			</stripBackground>
		</strip>
		<strip id="5">
			<stripBackground>			
				<img path="content/images/ltr/module8/m08s08/slk/Strip_05.png" minwidth="700" minheight="550"><![CDATA[]]></img>	
			</stripBackground>
		</strip>
		<strip id="6">
			<stripBackground>			
				<img path="content/images/ltr/module8/m08s08/slk/Strip_06.png" minwidth="700" minheight="550"><![CDATA[]]></img>	
			</stripBackground>
		</strip>
		<strip id="7">
			<stripBackground>			
				<img path="content/images/ltr/module8/m08s08/slk/Strip_07.png" minwidth="700" minheight="550"><![CDATA[]]></img>	
			</stripBackground>
		</strip>
		<strip id="8">
			<stripBackground>			
				<img path="content/images/ltr/module8/m08s08/slk/Strip_08.png" minwidth="700" minheight="550"><![CDATA[]]></img>	
			</stripBackground>
		</strip>
		<strip id="9">
			<stripBackground>			
				<img path="content/images/ltr/module8/m08s08/slk/Strip_09.png" minwidth="700" minheight="550"><![CDATA[]]></img>	
			</stripBackground>
		</strip>
		<strip id="10">
			<stripBackground>			
				<img path="content/images/ltr/module8/m08s08/slk/Strip_10.png" minwidth="700" minheight="550"><![CDATA[]]></img>	
			</stripBackground>
		</strip>
		<strip id="11">
			<stripBackground>			
				<img path="content/images/ltr/module8/m08s08/slk/Strip_11.png" minwidth="700" minheight="550"><![CDATA[]]></img>	
			</stripBackground>
		</strip>
		<strip id="12">
			<stripBackground>			
				<img path="content/images/ltr/module8/m08s08/slk/Strip_12.png" minwidth="700" minheight="550"><![CDATA[]]></img>	
			</stripBackground>
		</strip>
		<strip id="13">
			<stripBackground>			
				<img path="content/images/ltr/module8/m08s08/slk/Strip_13.png" minwidth="700" minheight="550"><![CDATA[]]></img>	
			</stripBackground>
		</strip>
		<strip id="14">
			<stripBackground>			
				<img path="content/images/ltr/module8/m08s08/slk/Strip_14.png" minwidth="700" minheight="550"><![CDATA[]]></img>	
			</stripBackground>
		</strip>
		<strip id="15">
			<stripBackground>			
				<img path="content/images/ltr/module8/m08s08/slk/Strip_15.png" minwidth="700" minheight="550"><![CDATA[]]></img>	
			</stripBackground>
		</strip>
		<strip id="16">
			<stripBackground>			
				<img path="content/images/ltr/module8/m08s08/slk/Strip_16.png" minwidth="700" minheight="550"><![CDATA[]]></img>	
			</stripBackground>
		</strip>
		<strip id="17">
			<stripBackground>			
				<img path="content/images/ltr/module8/m08s08/slk/Strip_17.png" minwidth="700" minheight="550"><![CDATA[]]></img>	
			</stripBackground>
		</strip>
		<strip id="18">
			<stripBackground>			
				<img path="content/images/ltr/module8/m08s08/slk/Strip_18.png" minwidth="700" minheight="550"><![CDATA[]]></img>	
			</stripBackground>
		</strip>
		<strip id="19">
			<stripBackground>			
				<img path="content/images/ltr/module8/m08s08/slk/Strip_19.png" minwidth="700" minheight="550"><![CDATA[]]></img>	
			</stripBackground>
		</strip>
		<strip id="20">
			<stripBackground>			
				<img path="content/images/ltr/module8/m08s08/slk/Strip_20.png" minwidth="700" minheight="550"><![CDATA[]]></img>	
			</stripBackground>
		</strip>
		<strip id="21">
			<stripBackground>			
				<img path="content/images/ltr/module8/m08s08/slk/Strip_21.png" minwidth="700" minheight="550"><![CDATA[]]></img>	
			</stripBackground>
		</strip>
		<strip id="22">
			<stripBackground>			
				<img path="content/images/ltr/module8/m08s08/slk/Strip_22.png" minwidth="700" minheight="550"><![CDATA[]]></img>	
			</stripBackground>
		</strip>
		<strip id="23">
			<stripBackground>			
				<img path="content/images/ltr/module8/m08s08/slk/Strip_23.png" minwidth="700" minheight="550"><![CDATA[]]></img>	
			</stripBackground>
		</strip>
		<strip id="24">
			<stripBackground>			
				<img path="content/images/ltr/module8/m08s08/slk/Strip_24.png" minwidth="700" minheight="550"><![CDATA[]]></img>	
			</stripBackground>
		</strip>
		<strip id="25">
			<stripBackground>			
				<img path="content/images/ltr/module8/m08s08/slk/Strip_25.png" minwidth="700" minheight="550"><![CDATA[]]></img>	
			</stripBackground>
		</strip>
		<strip id="26">
			<stripBackground>			
				<img path="content/images/ltr/module8/m08s08/slk/Strip_26.png" minwidth="700" minheight="550"><![CDATA[]]></img>	
			</stripBackground>
		</strip>
		<strip id="27">
			<stripBackground>			
				<img path="content/images/ltr/module8/m08s08/slk/Strip_27.png" minwidth="700" minheight="550"><![CDATA[]]></img>	
			</stripBackground>
		</strip>
		<strip id="28">
			<stripBackground>			
				<img path="content/images/ltr/module8/m08s08/slk/Strip_28.png" minwidth="700" minheight="550"><![CDATA[]]></img>	
			</stripBackground>
		</strip>
	</stripContent>
	
	<videoContent>
			 <videos path="content/slk/video/Confidential_Data.mp4" poster="content/slk/video/Confidential_Data.jpg" width="640" height="360">
				<cc time="0"><![CDATA[]]></cc> 
				<cc time="0"><![CDATA[Množstvo zaznamenaných informácií, vytvorených pred rokom 2000, je zhruba ekvivalentné množstvu údajov, ktoré sa v súčasnosti vytvárajú každé dva dni. ]]></cc> 
				<cc time="12"><![CDATA[To je veľa údajov a väčšina z nich je uložená online alebo na elektronických zariadeniach.]]></cc> 
				<cc time="21"><![CDATA[Ak používate prenosné zariadenia na prenášanie dôverných firemných informácií mimo pracoviska, máte povinnosť udržať ich v bezpečí.]]></cc> 
				<cc time="30"><![CDATA[Medzi tieto prenosné zariadenia patria prenosné počítače, notebooky, smartfóny, PDA a elektronické ukladacie zariadenia, ako sú napríklad USB kľúče a SD karty.]]></cc> 
				<cc time="43"><![CDATA[Poznajte, čo je na vašich zariadeniach a vždy majte informácie o tom, kde sú vaše zariadenia.]]></cc> 
				<cc time="48"><![CDATA[Položte si otázku: Musím mať na tomto zariadení dôverné informácie?]]></cc> 
				<cc time="57"><![CDATA[Ak je odpoveď nie, odstráňte informácie. ]]></cc> 
				<cc time="66"><![CDATA[Ak je odpoveď áno, zvážte, ako a kde použijete vaše zariadenie.]]></cc> 
				<cc time="73"><![CDATA[Naozaj musíte priniesť zariadenie s dôvernými firemnými údajmi na mimopracovnú udalosť? ]]></cc> 
				<cc time="78"><![CDATA[Môžete si byť istí, že nemôže byť sprístupnené ani ukradnuté? ]]></cc> 
				<cc time="82"><![CDATA[Inteligentní počítačoví kriminálnici môžu obísť heslá a šifrovanie na zariadeniach. ]]></cc> 
				<cc time="88"><![CDATA[Nedávajte im príležitosť. Nedovoľte, aby sa dostalo do ich rúk. ]]></cc> 
				<cc time="95"><![CDATA[Zariadenia môžu byť použité zločincami aj na narušenie bezpečnosti.]]></cc> 
				<cc time="101"><![CDATA[Ak nájdete USB kľúč, SD kartu alebo akýkoľvek iný typ úložného zariadenia, nezapájajte ho do vášho počítača.]]></cc> 
				<cc time="110"><![CDATA[Mohol by byť na ňom nahratý škodlivý softvér a otvoriť váš počítač útoku.]]></cc> 
				<cc time="116"><![CDATA[E-mailová komunikácia obsahuje veľké množstvo dôverných údajov.]]></cc> 
				<cc time="122"><![CDATA[Zločinci sa pokúšajú túto možnosť zneužiť pomocou e-mailov typu „phishing“. ]]></cc> 
				<cc time="127"><![CDATA[Nepredpokladajte, že e-mail je od toho, od koho tvrdí, že je, a nikdy nič nezverejňujte prostredníctvom e-mailu, ak si nie ste 100% istý, s kým komunikujete.]]></cc> 
				<cc time="135"><![CDATA[Informačný podvod nemusí byť na vysokej technickej úrovni.]]></cc> 
				<cc time="145"><![CDATA[Výtlačky môžu obsahovať dôverné údaje.]]></cc> 
				<cc time="150"><![CDATA[Nenechávajte výtlačky s dôvernými informáciami bez dozoru ani na stole, ani na firemnej tlačiarni alebo kopírke, prípadne v odpadkovom koši, kde by ich mohli neskôr získať zlodeji. ]]></cc> 
				<cc time="162"><![CDATA[Skartujte ich pred vyhodením.]]></cc> 
				<cc time="167"><![CDATA[Najlepší spôsob, ako sa chrániť pred náhodným zverejnením dôverných údajov, je obmedziť množstvo údajov, ktoré držíte, ku ktorým pristupujete a ktoré zdieľate.]]></cc> 
				<cc time="175"><![CDATA[Ponechajte si len to, čo potrebujete na prácu.]]></cc> 
				<cc time="182"><![CDATA[Informácie posielajte niekomu len vtedy, ak skutočne potrebujú všetky informácie, o ktoré žiadajú, aby vykonali svoju prácu a sú oprávnení na prístup k nim. ]]></cc> 
				<cc time="194"><![CDATA[Čím menej dôverných údajov držíte alebo zdieľate, tým menej riskujete stratu. ]]></cc> 
				<cc time="202"><![CDATA[Pamätajte si pravidlá OBMEDZIŤ–CHRÁNIŤ–ODSTRÁNIŤ a OBMEDZTE vždy to, čo používate, CHRÁŇTE to, čo držíte a VYMAŽTE to, čo už nie je potrebné.]]></cc> 
			</videos>	
	</videoContent>
	
</contents>