<?xml version="1.0" encoding="UTF-8"?>
<contents className="m10c03s18">
	<transcript>
		<text path="" id="0"><![CDATA[]]></text>
	</transcript>
	 <contentBackground cName="">		
		<img path="content/images/rtl/module10/m10c03/m10c03s18/contentBackground.jpg" minwidth="769"><![CDATA[]]></img>
	</contentBackground>
    <contentBg style=""></contentBg>
    <panelText>
		<text width="360px" height="auto" top="0px" position="relative" left="0px" padding="" cName=""><![CDATA[בהתחלה זה עובד טוב, נורית מקבלת קרדיט על כך שהיא עושה מכירות נוספות, ודויד יכול לקבל את הציוד והחומרים הדרושים לו בלי לגנוב אותם מ-Johnson Controls]]></text> 
		<text width="360px" height="auto" top="10px" position="relative" left="0px" padding="0 0 10px 0" cName=""><![CDATA[עם זאת, דויד מספר לכמה אנשים על המיזם הצדדי שלו ואחד מהם מתקשר לקו החם לנושאי יושרה. דויד מאבד את עבודתו והחברה פותחת בחקירה כדי לקבוע מי יצר את הזמנות הרכש המזויפות. זה רק עניין של זמן עד שיגיעו לנורית!]]></text>
	</panelText>	
	<pageTitle style="width: 360px;"></pageTitle>
	<instructionText style="width: 360px;">
		<text><![CDATA[לחץ על 'הבא' כדי לשקול מחדש את החלטתך וכדי לנסות שוב.]]></text>
	</instructionText>
</contents>