<?xml version="1.0" encoding="UTF-8"?>
<contents className="firstPageModule">
	<transcript>
		<text path="audio/module4/m04s01" id="0"><![CDATA[พวกเราทุกคนไม่ว่าจะมีหน้าที่ใด ต่างมีความรับผิดชอบที่จะต้องรักษาข้อมูลส่วนบุคคลของผู้ซื้อ พนักงาน และพาร์ทเนอร์ธุรกิจ ในโมดูลนี้ เราจะมาเรียนรู้กันว่าต้องทำอย่างไร]]></text>
	</transcript>
	 <contentBackground cName="">		
		<img path="content/images/ltr/module4/m04s01/contentBackground.jpg" minwidth="769"><![CDATA[พนักงานที่ทำงานในสภาพแวดล้อมออฟฟิศ]]></img>
	</contentBackground>
    <contentBg style=""></contentBg>
    <panelText>
		<text width="390px" height="auto" top="0px" position="relative" left="0px" padding="" cName=""><![CDATA[พวกเราทุกคนต่างมีความรับผิดชอบที่จะต้องรักษาข้อมูลส่วนบุคคลของผู้ซื้อ พนักงาน และพาร์ทเนอร์ธุรกิจ]]></text> 
		<text width="390px" height="auto" top="10px" position="relative" left="0px" padding="" cName=""><![CDATA[ข้อมูลที่สามารถใช้ระบุตัวตนใครบางคนนั้นจะต้องถูกรักษาไว้อย่างดี]]></text>
		<text width="390px" height="auto" top="20px" position="relative" left="0px" padding="0 0 20px 0" cName=""><![CDATA[ใช้ความระมัดระวังอย่างมากเมื่อโพสต์หรือทำงานอะไรบางอย่างบนพื้นที่สาธารณะ]]></text>
	</panelText>	
	<pageTitle style="width: 390px;"></pageTitle>
	<instructionText style="width: 390px;">
		<text><![CDATA[คลิกถัดไปเพื่อดำเนินการต่อ]]></text>
	</instructionText>
</contents>