<?xml version="1.0" encoding="UTF-8"?>
<contents type="revealCallOut2" className="m10c03s27">
	<transcript>
		<text path="" id="0"><![CDATA[]]></text>		
	</transcript>
	<contentText>
		<text style="font-size:14px;line-height:20px;"><![CDATA[夜遅くのクラブ。]]></text>
	</contentText>
	<contentBackground>
		<img path="content/images/ltr/module10/m10c03/m10c03s27/contentBackground.jpg" minwidth="769"><![CDATA[予期せぬ出来事]]></img>
	</contentBackground>	
	 <contentBg style=""></contentBg>
	<pageTitle style="width: 574px;"></pageTitle>
	<instructionText style="width: 574px;">
		<text><![CDATA[それぞれの人物をクリックします。]]></text>
		<text><![CDATA[「次へ」をクリックして、選択を再度考え、再挑戦してください。]]></text>
	</instructionText>	
	<revealCallOutContent style="top:158px;">
		<revealCallOut width="300px" height="196px" top="15px" left="370px" ticktop="5px" tickleft="3px">			
			<img path="content/images/ltr/module10/m10c03/m10c03s27/img_01.png" minwidth="769"><![CDATA[]]></img>
			<buttonText style="height: 56px;"><![CDATA[カルロス]]></buttonText>
			<popupArrow style="left:140px; top: -15px;" />
			<popText showHeader="true" arrowleft="" style="height: 205px;top:-227px; display: block; left: 370px; width: 608px;line-height:20px;">			
				<text style="margin-bottom: 7px;font-size:15px;line-height:20px;"><![CDATA[私は飲み過ぎて、夜更けには泥酔していました。]]></text>						
				<text style="margin-bottom: 7px;font-size:15px;line-height:20px;"><![CDATA[誰かが写真を撮りました。私は覚えていません！ 彼は写真をInstagramに投稿し、すぐにみんながそれらを見ました。私の上司もです。]]></text>						
			</popText>
		</revealCallOut>
		
		<revealCallOut width="300px" height="196px" top="15px" left="678px" ticktop="5px" tickleft="3px">			
			<img path="content/images/ltr/module10/m10c03/m10c03s27/img_02.png" minwidth="769"><![CDATA[]]></img>
			<buttonText style="height: 56px;"><![CDATA[チェン（カルロスの上司）]]></buttonText>
			<popupArrow style="left:460px; top: -15px;" />
			<popText showHeader="true" arrowleft="" style="height: 205px;top:-227px; display: block; left: 370px; width: 608px;">
				<text style="margin-bottom: 10px;font-size:15px;line-height:20px;"><![CDATA[カルロスはいくつか説明することがあります。 彼はビジネスに関連したイベントで、Johnson Controlsの代表として参加していました。 彼は風俗営業をしている場所に関わることを避けるように、より努力するべきです。 そして、彼は泥酔してはいけませんでした。 ]]></text>					
				<text style="margin-bottom: 0px;font-size:15px;line-height:20px;"><![CDATA[カルロスは間違った判断をしたために、処分を下されることになりました。]]></text>					
			</popText>
		</revealCallOut>
		
	</revealCallOutContent>	
</contents>