<?xml version="1.0" encoding="UTF-8"?>
<contents className="m08s10" type="multiTab" defaultTab="1" isRandom="true" onlySticksCorrect="false">
	<transcript>
		<text id="0" path="audio/module8/m08s10"><![CDATA[Portanto, vamos aplicar isso à realidade. Como você lidaria com as seguintes situações? Associe cada situação na esquerda à solução correta na direita e clique em Enviar.]]></text>
	</transcript>
	<contentText>
		<text><![CDATA[Mostre que você sabe o que fazer em cada uma dessas situações. ]]></text>
	</contentText>
	<contentBackground cName="">		
		<img path="content/images/ltr/module8/m08s10/contentBackground.jpg" minwidth="769"><![CDATA[]]></img>
	</contentBackground>
	<contentBg style="width: 990px;right: 10px;top: 30px;padding: 0;" wtbgStyle="padding: 15px 15px;"></contentBg>
	<pageTitle style=""></pageTitle>
	<buttonText>		
		<text style="position: relative;left:892px;top: -15px;"><![CDATA[ENVIAR]]></text>
	</buttonText>
	<instructionText>
		<text><![CDATA[Selecione um item na primeira coluna e arraste as setas para a solução correspondente na segunda coluna. Quando estiver pronto, clique em Enviar.]]></text>
		<text><![CDATA[Clique em Próximo para continuar.]]></text>
	</instructionText>
	<matchingActivity style="margin:35px auto 0 auto;" lineHolderW="990" lineHolderH="250">
		<leftSideTabs>
			<heder><![CDATA[A SITUAÇÃO]]></heder>
			
			<tab id="1" style="height:100px" dragPosition="left: 430px;top: 8px;z-index: 5;height: 100px;">
				<leftIcon style="height:100px" path="content/images/ltr/module8/m08s10/img01.png"><![CDATA[Pessoa trabalhando em componentes]]></leftIcon>
				<dragIcon path="content/images/ltr/arrow.png" style=""><![CDATA[]]></dragIcon>
				<text style=""><![CDATA[Você está trabalhando com fornecedores em potencial que estão participando de uma licitação para fornecer componentes de um novo produto ]]></text>				
			</tab>			
			<tab id="2" style="height:100px" dragPosition="left:430px; top:119px;z-index:5;height:100px">
				<leftIcon style="height:100px" path="content/images/ltr/module8/m08s10/img02.png"><![CDATA[Pessoa selecionando ícone para abrir e-mail]]></leftIcon>
				<dragIcon path="content/images/ltr/arrow.png" style=""><![CDATA[]]></dragIcon>
				<text style=""><![CDATA[Você está trabalhando em um documento que precisa terminar, então você considera enviá-lo para si mesmo em casa]]></text>
			</tab>
		</leftSideTabs>	
		<rightSideTabs>		
			<heder><![CDATA[A SOLUÇÃO]]></heder>
			<tab id="2" style="height:100px" dropPosition="left: 528px;top: 8px;height: 100px;">
				<text style=""><![CDATA[Encontre outra maneira de acessar o documento, pois e-mails podem ser perdidos, hackeados ou desviados]]></text>
				<rightIcon style="height:100px" path="content/images/ltr/module8/m08s10/img04.png"><![CDATA[Ícone de pasta]]></rightIcon>
			</tab>	
			<tab id="1" style="height:100px" dropPosition="left: 528px;top: 119px;height: 100px;">
				<text><![CDATA[Exija que assinem acordos de não divulgação antes de compartilhar informações de um novo produto e marcá-las como confidenciais ]]></text>
				<rightIcon style="height:100px" path="content/images/ltr/module8/m08s10/img03.png"><![CDATA[Pessoa assinando um NDA]]></rightIcon>
			</tab>	
		</rightSideTabs>		
		<feedback type="normal">
			<correct id="1" style="padding:10px;position: relative;width: 960px;top: -15px;">
				<text style=""><![CDATA[É isso! Você acertou todas! ]]></text>
			</correct>			
			<incorrect id="2" style="padding:10px;position: relative;width: 960px;top: -15px;">
				<text style=""><![CDATA[Não está correto]]></text>
			</incorrect>			
		</feedback>		
	</matchingActivity>
</contents>