<?xml version="1.0" encoding="utf-8" ?>
<contents className="firstPageModule">
	<transcript>
		<text path="audio/module2/m02s01" id="0" ><![CDATA[Gifts and entertainment are often a key part of doing business. In this module, learn what you need to do to comply with our policies and the law when giving or accepting gifts and entertainment.]]></text>
	</transcript>
	 <contentBackground cName="" >		
		<img path="content/images/ltr/module2/m02s01/contentBackground.jpg"  minwidth="769"><![CDATA[An office]]></img>
	</contentBackground>
    <contentBg style="" ></contentBg>
    <panelText>
		<text width="420px" height="auto" top="0px" position="relative" left="0px" padding="" cName="" ><![CDATA[Exchanging gifts or entertainment can help build business relationships, but it can also create problems if not handled properly.]]></text> 
		<text width="420px" height="auto" top="10px" position="relative" left="0px" padding="" cName="" ><![CDATA[Follow our guidelines to avoid misusing gifts or entertainment.]]></text>
		<text width="420px" height="auto" top="20px" position="relative" left="0px" padding="0 0 20px 0" cName="" ><![CDATA[Recognize that stricter rules apply to gifts or entertainment for government officials.]]></text>
	</panelText>	
	<pageTitle style="width: 420px;"></pageTitle>
	<instructionText style="width: 420px;" >
		<text ><![CDATA[Click on Next (bottom right arrow) to continue.]]></text>
	</instructionText>
</contents>