<?xml version="1.0" encoding="UTF-8"?>
<contents className="m06s09 verticallyCenterPageData">
	<transcript>
		<text path="audio/module6/m06s09" id="0"><![CDATA[Johnson Controls 期望全體員工能了解競爭法對於他們在工作時的行動和決策所產生的影響。]]></text>
	</transcript>
	 <contentBackground>		
		<img path="content/images/ltr/module6/m06s09/contentBackground.jpg" minwidth="769"><![CDATA[員工]]></img>
	</contentBackground>
	 <contentBg style=""></contentBg>
    <panelText>
		<text width="420px" height="auto" top="0px" position="relative" left="0px" padding="" cName=""><![CDATA[規範公平競爭的法律相當複雜，因此若對於特定業務行為有任何疑問，請務必洽詢 Johnson Controls 法律部門或合規團隊的成員。
]]></text>
		<text width="420px" height="auto" top="10px" position="relative" left="0px" padding="" cName=""><![CDATA[如對競爭法律有任何疑問：<ul> <li>向法務或合規團隊尋求指導</li> <li>參閱 <a href="content/nan/pdf/Antitrust_Fair_Competition_Policy.pdf" target="_blank" class="aLinkColor">Johnson Controls 的全球反托拉斯與公平競爭政策</a></li> </ul>]]></text>
		<text width="420px" height="auto" top="20px" position="relative" left="0px" padding="0 0 20px 0" cName=""><![CDATA[若目睹或懷疑任何違反競爭法或 Johnson Controls 政策的行為，您有責任提報。 您可以： <ul> <li>告訴您的經理或是法務或合規團隊</li> <li>撥打 <a href="http://www.johnsoncontrolsintegrityhelpline.com" target="_blank" class="aLinkColor">Johnson Controls 誠信熱線</a>，記錄您的疑慮</li> </ul>]]></text>
	</panelText>	
	<pageTitle style="width: 420px;"></pageTitle>
	<instructionText style="width: 420px;">
		<text><![CDATA[按「下一步」返回「首頁」功能表。]]></text>
	</instructionText>
</contents>