<?xml version="1.0" encoding="UTF-8"?>
<contents className="m01s08 verticallyCenterPageData">
	<transcript>
		<text path="audio/module1/m01s08" id="0"><![CDATA[Wenn Sie in einen potenziellen Interessenkonflikt geraten, legen Sie ihn offen!]]></text>
	</transcript>
	 <contentBackground>		
		<img path="content/images/ltr/module1/m01s08/contentBackground.jpg" minwidth="769"><![CDATA[Frau telefoniert mit der Personalabteilung]]></img>
	</contentBackground>
	 <contentBg style=""></contentBg>
    <panelText>
		<text width="480px" height="auto" top="0px" position="relative" left="0px" padding="" cName=""><![CDATA[Interessenkonflikte sind nicht immer offensichtlich.]]></text>
		<text width="480px" height="auto" top="10px" position="relative" left="0px" padding="0 0 10px 0" cName=""><![CDATA[<ul> <li>Geraten Sie jedoch nicht in Versuchung, einfach abzuwarten, was passiert und die Offenlegung der Situation hinauszuzögern. Unser Prozess ist darauf ausgelegt, Johnson Controls bei der angemessenen Bewertung solcher Situationen zu unterstützen.</li> <li>Im Zweifelsfall:<ul> <li>Bitten Sie Ihren Vorgesetzten, die Personalabteilung, die Rechtsabteilung oder das Compliance-Team um Rat.</li> <li>Sehen Sie in der <a href="content/deu/pdf/Conflict_Of_Interest_Policy.pdf" target="_blank" class="aLinkColor">Richtlinie für Interessenkonflikte von Johnson Controls nach</a>. </li> <li>Füllen Sie das Formular zu Interessenkonflikten unter dem folgenden Link aus:<br/><a href="http://complianceforms.jci.com" target="_blank" class="aLinkColor">http://complianceforms.jci.com</a></li> </ul></li> </ul>]]></text>
	</panelText>	
	<pageTitle style="width: 480px;"></pageTitle>
	<instructionText style="width: 480px;">
		<text><![CDATA[Klicken Sie auf „Weiter“, um zum Hauptmenü zurückzukehren.]]></text>
	</instructionText>
</contents>